scinstr/cnt/__init__.py
scinstr/cnt/cnt532x0a.py
scinstr/cnt/cnt_emul.py
scinstr/cnt/constants.py
scinstr/cnt/qcnt532x0a.py
scinstr/cnt/scnt532x0a.py
scinstr/compressor/__init__.py
scinstr/compressor/cp2800.py
scinstr/daq/__init__.py
scinstr/daq/constants.py
scinstr/daq/daq34972a.py
scinstr/daq/labjack/__init__.py
scinstr/daq/labjack/constants.py
scinstr/daq/labjack/convert_data.py
scinstr/daq/labjack/t7.py
scinstr/daq/labjack/t7eth.py
scinstr/daq/labjack/t7usb.py
scinstr/dmm/__init__.py
scinstr/dmm/constants.py
scinstr/dmm/dmm34461a.py
scinstr/dmm/dmm34461a_emul.py
scinstr/dmm/dmm4050.py
scinstr/dmm/dmm_emul.py
scinstr/dmm/dmm_emul_core.py
scinstr/dmm/qdmm34461a.py
scinstr/dmm/sdm3065x.py
scinstr/dmm/sdm3065x_emul.py
scinstr/dmm/sdmm34461a.py
scinstr/lockin/__init__.py
scinstr/lockin/li5645.py
scinstr/lockin/li5645_services.py
scinstr/lockin/sr8x0.py
scinstr/lockin/sr8x0ethernet.py
scinstr/lockin/sr8x0serial.py
scinstr/phimeter/__init__.py
scinstr/phimeter/fswpacq.py
scinstr/tctrl/__init__.py
scinstr/tctrl/constants.py
scinstr/tctrl/cryocon24c.py
scinstr/tctrl/l350.py
scinstr/tctrl/mercury_itc.py
scinstr/vacuum/__init__.py
scinstr/vacuum/centerone.py
scinstr/vacuum/d395.py
scinstr/vacuum/gauge.py
scinstr/vacuum/tpg261.py
scinstr/vna/__init__.py
scinstr/vna/n523x.py
scinstr-0.4.9.dist-info/licenses/LICENSE.txt
scinstr-0.4.9.dist-info/METADATA
scinstr-0.4.9.dist-info/WHEEL
scinstr-0.4.9.dist-info/top_level.txt
scinstr-0.4.9.dist-info/RECORD
