Metadata-Version: 2.4
Name: scinstr
Version: 0.4.9
Summary: Drivers to handle various scientific instruments (DMM, frequency counter, DAQ, VNA...). Include also some cli script.
Home-page: https://gitlab.com/bendub/scinstr
Author: Benoit Dubois
Author-email: benoit.dubois@femto-engineering.fr
Classifier: Development Status :: 4 - Beta
Classifier: Environment :: Console
Classifier: Intended Audience :: Developers
Classifier: License :: OSI Approved :: GNU Lesser General Public License v3 or later (LGPLv3+)
Classifier: Natural Language :: English
Classifier: Operating System :: POSIX :: Linux
Classifier: Programming Language :: Python
Classifier: Topic :: Scientific/Engineering
License-File: LICENSE.txt
Requires-Dist: pyusb
Requires-Dist: PyVISA
Requires-Dist: PyVISA-py
Requires-Dist: pyserial
Requires-Dist: python-usbtmc
Requires-Dist: pymodbus
Provides-Extra: pure-python-signalslot-facilities
Requires-Dist: signalslot; extra == "pure-python-signalslot-facilities"
Dynamic: author
Dynamic: author-email
Dynamic: classifier
Dynamic: home-page
Dynamic: license-file
Dynamic: provides-extra
Dynamic: requires-dist
Dynamic: summary
